{"id":708,"name":"phantump","image":"https://raw.githubusercontent.com/PokeAPI/sprites/master/sprites/pokemon/other/home/708.png","types":["ghost","grass"],"abilities":["natural-cure","frisk","harvest"],"height":4,"weight":70,"stats":[{"base_stat":43,"effort":0,"stat":{"name":"hp","url":"https://pokeapi.co/api/v2/stat/1/"}},{"base_stat":70,"effort":1,"stat":{"name":"attack","url":"https://pokeapi.co/api/v2/stat/2/"}},{"base_stat":48,"effort":0,"stat":{"name":"defense","url":"https://pokeapi.co/api/v2/stat/3/"}},{"base_stat":50,"effort":0,"stat":{"name":"special-attack","url":"https://pokeapi.co/api/v2/stat/4/"}},{"base_stat":60,"effort":0,"stat":{"name":"special-defense","url":"https://pokeapi.co/api/v2/stat/5/"}},{"base_stat":38,"effort":0,"stat":{"name":"speed","url":"https://pokeapi.co/api/v2/stat/6/"}}],"base_experience":62,"total_stats":309,"stat_category":"physical-attacker","generation":"generation-vi","is_legendary":false,"is_mythical":false,"habitat":null,"color":"brown","shape":"arms","capture_rate":120,"growth_rate":"medium","egg_groups":["plant","indeterminate"],"flavor_text":"These Pokémon are created when spirits possess rotten tree stumps. They prefer to live in abandoned forests.","rarity_tier":"uncommon","size_category":"small","evolutionChain":{"species":"phantump","speciesId":708,"trigger":null,"triggerDetail":null,"evolvesTo":[{"species":"trevenant","speciesId":709,"trigger":"trade","triggerDetail":"Trade","evolvesTo":[]}]},"moves":[{"name":"tackle","type":"normal","power":40,"accuracy":100,"pp":35,"damageClass":"physical","effect":"Inflicts regular damage with no additional effect.","learnMethod":"level-up","levelLearned":1},{"name":"astonish","type":"ghost","power":30,"accuracy":100,"pp":15,"damageClass":"physical","effect":"Has a 30% chance to make the target flinch.","learnMethod":"level-up","levelLearned":1},{"name":"branch-poke","type":"grass","power":40,"accuracy":100,"pp":40,"damageClass":"physical","effect":"Inflicts regular damage with no additional effect.","learnMethod":"level-up","levelLearned":4},{"name":"leech-seed","type":"grass","power":null,"accuracy":90,"pp":10,"damageClass":"status","effect":"Seeds the target, stealing HP from it every turn.","learnMethod":"level-up","levelLearned":8},{"name":"feint-attack","type":"dark","power":60,"accuracy":null,"pp":20,"damageClass":"physical","effect":"Never misses.","learnMethod":"level-up","levelLearned":19},{"name":"growth","type":"normal","power":null,"accuracy":null,"pp":20,"damageClass":"status","effect":"Raises the user’s Attack and Special Attack by one stage.","learnMethod":"level-up","levelLearned":24},{"name":"horn-leech","type":"grass","power":75,"accuracy":100,"pp":10,"damageClass":"physical","effect":"Drains half the damage inflicted to heal the user.","learnMethod":"level-up","levelLearned":28},{"name":"ingrain","type":"grass","power":null,"accuracy":null,"pp":20,"damageClass":"status","effect":"Prevents the user from leaving battle.  User regains 1/16 of its max HP every turn.","learnMethod":"level-up","levelLearned":40},{"name":"wood-hammer","type":"grass","power":120,"accuracy":100,"pp":15,"damageClass":"physical","effect":"User receives 1/3 the damage inflicted in recoil.","learnMethod":"level-up","levelLearned":44},{"name":"destiny-bond","type":"ghost","power":null,"accuracy":null,"pp":5,"damageClass":"status","effect":"If the user faints this turn, the target automatically will, too.","learnMethod":"level-up","levelLearned":48},{"name":"forests-curse","type":"grass","power":null,"accuracy":100,"pp":20,"damageClass":"status","effect":"Adds grass to the target’s types.","learnMethod":"level-up","levelLearned":52},{"name":"attract","type":"normal","power":null,"accuracy":100,"pp":15,"damageClass":"status","effect":"Target falls in love if it has the opposite gender, and has a 50% chance to refuse attacking the user.","learnMethod":"machine","levelLearned":null},{"name":"bulldoze","type":"ground","power":60,"accuracy":100,"pp":20,"damageClass":"physical","effect":"Has a 100% chance to lower the target’s Speed by one stage.","learnMethod":"machine","levelLearned":null},{"name":"confide","type":"normal","power":null,"accuracy":null,"pp":20,"damageClass":"status","effect":"Lowers the target’s Special Attack by one stage.","learnMethod":"machine","levelLearned":null},{"name":"confuse-ray","type":"ghost","power":null,"accuracy":100,"pp":10,"damageClass":"status","effect":"Confuses the target.","learnMethod":"machine","levelLearned":null},{"name":"curse","type":"ghost","power":null,"accuracy":null,"pp":10,"damageClass":"status","effect":"Ghosts pay half their max HP to hurt the target every turn.  Others decrease Speed but raise Attack and Defense.","learnMethod":"machine","levelLearned":null},{"name":"cut","type":"normal","power":50,"accuracy":95,"pp":30,"damageClass":"physical","effect":"Inflicts regular damage with no additional effect.","learnMethod":"machine","levelLearned":null},{"name":"dark-pulse","type":"dark","power":80,"accuracy":100,"pp":15,"damageClass":"special","effect":"Has a 20% chance to make the target flinch.","learnMethod":"machine","levelLearned":null},{"name":"dig","type":"ground","power":80,"accuracy":100,"pp":10,"damageClass":"physical","effect":"User digs underground, dodging all attacks, and hits next turn.","learnMethod":"machine","levelLearned":null},{"name":"double-team","type":"normal","power":null,"accuracy":null,"pp":15,"damageClass":"status","effect":"Raises the user’s evasion by one stage.","learnMethod":"machine","levelLearned":null},{"name":"dream-eater","type":"psychic","power":100,"accuracy":100,"pp":15,"damageClass":"special","effect":"Only works on sleeping Pokémon.  Drains half the damage inflicted to heal the user.","learnMethod":"machine","levelLearned":null},{"name":"endure","type":"normal","power":null,"accuracy":null,"pp":10,"damageClass":"status","effect":"Prevents the user’s HP from lowering below 1 this turn.","learnMethod":"machine","levelLearned":null},{"name":"energy-ball","type":"grass","power":90,"accuracy":100,"pp":10,"damageClass":"special","effect":"Has a 10% chance to lower the target’s Special Defense by one stage.","learnMethod":"machine","levelLearned":null},{"name":"facade","type":"normal","power":70,"accuracy":100,"pp":20,"damageClass":"physical","effect":"Power doubles if user is burned, paralyzed, or poisoned.","learnMethod":"machine","levelLearned":null},{"name":"foul-play","type":"dark","power":95,"accuracy":100,"pp":15,"damageClass":"physical","effect":"Calculates damage with the target’s attacking stat.","learnMethod":"machine","levelLearned":null},{"name":"frustration","type":"normal","power":null,"accuracy":100,"pp":20,"damageClass":"physical","effect":"Power increases as happiness decreases, up to a maximum of 102.","learnMethod":"machine","levelLearned":null},{"name":"giga-drain","type":"grass","power":75,"accuracy":100,"pp":10,"damageClass":"special","effect":"Drains half the damage inflicted to heal the user.","learnMethod":"machine","levelLearned":null},{"name":"grass-knot","type":"grass","power":null,"accuracy":100,"pp":20,"damageClass":"special","effect":"Inflicts more damage to heavier targets, with a maximum of 120 power.","learnMethod":"machine","levelLearned":null},{"name":"grassy-glide","type":"grass","power":55,"accuracy":100,"pp":20,"damageClass":"physical","effect":"Inflicts regular damage with no additional effect.","learnMethod":"machine","levelLearned":null},{"name":"grassy-terrain","type":"grass","power":null,"accuracy":null,"pp":10,"damageClass":"status","effect":"For five turns, heals all Pokémon on the ground for 1/16 max HP each turn and strengthens their grass moves to 1.5× their power.","learnMethod":"machine","levelLearned":null},{"name":"hex","type":"ghost","power":65,"accuracy":100,"pp":10,"damageClass":"special","effect":"Has double power if the target has a major status ailment.","learnMethod":"machine","levelLearned":null},{"name":"hidden-power","type":"normal","power":60,"accuracy":100,"pp":15,"damageClass":"special","effect":"Power and type depend upon user’s IVs.  Power can range from 30 to 70.","learnMethod":"machine","levelLearned":null},{"name":"imprison","type":"psychic","power":null,"accuracy":null,"pp":10,"damageClass":"status","effect":"Prevents the target from using any moves that the user also knows.","learnMethod":"machine","levelLearned":null},{"name":"lash-out","type":"dark","power":75,"accuracy":100,"pp":5,"damageClass":"physical","effect":"Inflicts regular damage with no additional effect.","learnMethod":"machine","levelLearned":null},{"name":"magical-leaf","type":"grass","power":60,"accuracy":null,"pp":20,"damageClass":"special","effect":"Never misses.","learnMethod":"machine","levelLearned":null},{"name":"nature-power","type":"normal","power":null,"accuracy":null,"pp":20,"damageClass":"status","effect":"Uses a move which depends upon the terrain.","learnMethod":"machine","levelLearned":null},{"name":"night-shade","type":"ghost","power":null,"accuracy":100,"pp":15,"damageClass":"special","effect":"Inflicts damage equal to the user’s level.","learnMethod":"machine","levelLearned":null},{"name":"pain-split","type":"normal","power":null,"accuracy":null,"pp":20,"damageClass":"status","effect":"Sets the user’s and targets’s HP to the average of their current HP.","learnMethod":"machine","levelLearned":null},{"name":"phantom-force","type":"ghost","power":90,"accuracy":100,"pp":10,"damageClass":"physical","effect":"User vanishes, dodging all attacks, and hits next turn.  Hits through Protect and Detect.","learnMethod":"machine","levelLearned":null},{"name":"poison-jab","type":"poison","power":80,"accuracy":100,"pp":20,"damageClass":"physical","effect":"Has a 30% chance to poison the target.","learnMethod":"machine","levelLearned":null},{"name":"poltergeist","type":"ghost","power":110,"accuracy":90,"pp":5,"damageClass":"physical","effect":"Inflicts regular damage with no additional effect.","learnMethod":"machine","levelLearned":null},{"name":"protect","type":"normal","power":null,"accuracy":null,"pp":10,"damageClass":"status","effect":"Prevents any moves from hitting the user this turn.","learnMethod":"machine","levelLearned":null},{"name":"psych-up","type":"normal","power":null,"accuracy":null,"pp":10,"damageClass":"status","effect":"Discards the user’s stat changes and copies the target’s.","learnMethod":"machine","levelLearned":null},{"name":"psychic","type":"psychic","power":90,"accuracy":100,"pp":10,"damageClass":"special","effect":"Has a 10% chance to lower the target’s Special Defense by one stage.","learnMethod":"machine","levelLearned":null},{"name":"rain-dance","type":"water","power":null,"accuracy":null,"pp":5,"damageClass":"status","effect":"Changes the weather to rain for five turns.","learnMethod":"machine","levelLearned":null},{"name":"reflect","type":"psychic","power":null,"accuracy":null,"pp":20,"damageClass":"status","effect":"Reduces damage from physical attacks by half.","learnMethod":"machine","levelLearned":null},{"name":"rest","type":"psychic","power":null,"accuracy":null,"pp":5,"damageClass":"status","effect":"User sleeps for two turns, completely healing itself.","learnMethod":"machine","levelLearned":null},{"name":"return","type":"normal","power":null,"accuracy":100,"pp":20,"damageClass":"physical","effect":"Power increases with happiness, up to a maximum of 102.","learnMethod":"machine","levelLearned":null},{"name":"rock-slide","type":"rock","power":75,"accuracy":90,"pp":10,"damageClass":"physical","effect":"Has a 30% chance to make the target flinch.","learnMethod":"machine","levelLearned":null},{"name":"rock-smash","type":"fighting","power":40,"accuracy":100,"pp":15,"damageClass":"physical","effect":"Has a 50% chance to lower the target’s Defense by one stage.","learnMethod":"machine","levelLearned":null},{"name":"round","type":"normal","power":60,"accuracy":100,"pp":15,"damageClass":"special","effect":"Has double power if it’s used more than once per turn.","learnMethod":"machine","levelLearned":null},{"name":"safeguard","type":"normal","power":null,"accuracy":null,"pp":25,"damageClass":"status","effect":"Protects the user’s field from major status ailments and confusion for five turns.","learnMethod":"machine","levelLearned":null},{"name":"secret-power","type":"normal","power":70,"accuracy":100,"pp":20,"damageClass":"physical","effect":"Has a 30% chance to inflict a status effect which depends upon the terrain.","learnMethod":"machine","levelLearned":null},{"name":"seed-bomb","type":"grass","power":80,"accuracy":100,"pp":15,"damageClass":"physical","effect":"Inflicts regular damage with no additional effect.","learnMethod":"machine","levelLearned":null},{"name":"shadow-ball","type":"ghost","power":80,"accuracy":100,"pp":15,"damageClass":"special","effect":"Has a 20% chance to lower the target’s Special Defense by one stage.","learnMethod":"machine","levelLearned":null},{"name":"shadow-claw","type":"ghost","power":70,"accuracy":100,"pp":15,"damageClass":"physical","effect":"Has an increased chance for a critical hit.","learnMethod":"machine","levelLearned":null},{"name":"skill-swap","type":"psychic","power":null,"accuracy":null,"pp":10,"damageClass":"status","effect":"User and target swap abilities.","learnMethod":"machine","levelLearned":null},{"name":"skitter-smack","type":"bug","power":70,"accuracy":90,"pp":10,"damageClass":"physical","effect":"Inflicts regular damage with no additional effect.","learnMethod":"machine","levelLearned":null},{"name":"sleep-talk","type":"normal","power":null,"accuracy":null,"pp":10,"damageClass":"status","effect":"Randomly uses one of the user’s other three moves.  Only works if the user is sleeping.","learnMethod":"machine","levelLearned":null},{"name":"snore","type":"normal","power":50,"accuracy":100,"pp":15,"damageClass":"special","effect":"Has a 30% chance to make the target flinch.  Only works if the user is sleeping.","learnMethod":"machine","levelLearned":null},{"name":"solar-beam","type":"grass","power":120,"accuracy":100,"pp":10,"damageClass":"special","effect":"Requires a turn to charge before attacking.","learnMethod":"machine","levelLearned":null},{"name":"spite","type":"ghost","power":null,"accuracy":100,"pp":10,"damageClass":"status","effect":"Lowers the PP of the target’s last used move by 4.","learnMethod":"machine","levelLearned":null},{"name":"strength","type":"normal","power":80,"accuracy":100,"pp":15,"damageClass":"physical","effect":"Inflicts regular damage with no additional effect.","learnMethod":"machine","levelLearned":null},{"name":"substitute","type":"normal","power":null,"accuracy":null,"pp":10,"damageClass":"status","effect":"Transfers 1/4 of the user’s max HP into a doll, protecting the user from further damage or status changes until it breaks.","learnMethod":"machine","levelLearned":null},{"name":"sunny-day","type":"fire","power":null,"accuracy":null,"pp":5,"damageClass":"status","effect":"Changes the weather to sunny for five turns.","learnMethod":"machine","levelLearned":null},{"name":"swagger","type":"normal","power":null,"accuracy":85,"pp":15,"damageClass":"status","effect":"Raises the target’s Attack by two stages and confuses the target.","learnMethod":"machine","levelLearned":null},{"name":"tera-blast","type":"normal","power":80,"accuracy":100,"pp":10,"damageClass":"special","effect":"","learnMethod":"machine","levelLearned":null},{"name":"thief","type":"dark","power":60,"accuracy":100,"pp":25,"damageClass":"physical","effect":"Takes the target’s item.","learnMethod":"machine","levelLearned":null},{"name":"toxic","type":"poison","power":null,"accuracy":90,"pp":10,"damageClass":"status","effect":"Badly poisons the target, inflicting more damage every turn.","learnMethod":"machine","levelLearned":null},{"name":"trailblaze","type":"grass","power":50,"accuracy":100,"pp":20,"damageClass":"physical","effect":"","learnMethod":"machine","levelLearned":null},{"name":"trick","type":"psychic","power":null,"accuracy":100,"pp":10,"damageClass":"status","effect":"User and target swap items.","learnMethod":"machine","levelLearned":null},{"name":"trick-room","type":"psychic","power":null,"accuracy":null,"pp":5,"damageClass":"status","effect":"For five turns, slower Pokémon will act before faster Pokémon.","learnMethod":"machine","levelLearned":null},{"name":"venom-drench","type":"poison","power":null,"accuracy":100,"pp":20,"damageClass":"status","effect":"Lowers the target’s Attack, Special Attack, and Speed by one stage if it is poisoned.","learnMethod":"machine","levelLearned":null},{"name":"will-o-wisp","type":"fire","power":null,"accuracy":85,"pp":15,"damageClass":"status","effect":"Burns the target.","learnMethod":"machine","levelLearned":null},{"name":"ally-switch","type":"psychic","power":null,"accuracy":null,"pp":15,"damageClass":"status","effect":"User switches places with the friendly Pokémon opposite it.","learnMethod":"egg","levelLearned":null},{"name":"bestow","type":"normal","power":null,"accuracy":null,"pp":15,"damageClass":"status","effect":"Gives the user’s held item to the target.","learnMethod":"egg","levelLearned":null},{"name":"disable","type":"normal","power":null,"accuracy":100,"pp":20,"damageClass":"status","effect":"Disables the target’s last used move for 1-8 turns.","learnMethod":"egg","levelLearned":null},{"name":"grudge","type":"ghost","power":null,"accuracy":null,"pp":5,"damageClass":"status","effect":"If the user faints this turn, the PP of the move that fainted it drops to 0.","learnMethod":"egg","levelLearned":null},{"name":"power-up-punch","type":"fighting","power":40,"accuracy":100,"pp":20,"damageClass":"physical","effect":"Raises the user’s Attack by one stage after inflicting damage.","learnMethod":"egg","levelLearned":null},{"name":"sucker-punch","type":"dark","power":70,"accuracy":100,"pp":5,"damageClass":"physical","effect":"Only works if the target is about to use a damaging move.","learnMethod":"egg","levelLearned":null},{"name":"magic-coat","type":"psychic","power":null,"accuracy":null,"pp":15,"damageClass":"status","effect":"Reflects back the first effect move used on the user this turn.","learnMethod":"tutor","levelLearned":null},{"name":"role-play","type":"psychic","power":null,"accuracy":null,"pp":10,"damageClass":"status","effect":"Copies the target’s ability.","learnMethod":"tutor","levelLearned":null},{"name":"telekinesis","type":"psychic","power":null,"accuracy":null,"pp":15,"damageClass":"status","effect":"Moves have 100% accuracy against the target for three turns.","learnMethod":"tutor","levelLearned":null},{"name":"worry-seed","type":"grass","power":null,"accuracy":100,"pp":10,"damageClass":"status","effect":"Changes the target’s ability to Insomnia.","learnMethod":"tutor","levelLearned":null}],"abilitiesDetailed":[{"name":"natural-cure","isHidden":false,"effect":"Cures any major status ailment upon switching out."},{"name":"frisk","isHidden":false,"effect":"Reveals an opponent's held item upon entering battle."},{"name":"harvest","isHidden":true,"effect":"Has a 50% chance of restoring a used Berry after each turn if the Pokémon has held no items in the meantime."}],"sprites":{"official":"https://raw.githubusercontent.com/PokeAPI/sprites/master/sprites/pokemon/other/official-artwork/708.png","shiny":"https://raw.githubusercontent.com/PokeAPI/sprites/master/sprites/pokemon/other/official-artwork/shiny/708.png","home":"https://raw.githubusercontent.com/PokeAPI/sprites/master/sprites/pokemon/other/home/708.png","animated":null},"forms":[],"encounters":[{"location":"Kalos Route 16 Area","games":["x","y"]},{"location":"Memorial Hill Area","games":["sun","moon","ultra-sun","ultra-moon"]},{"location":"Tapu Village Area","games":["ultra-sun","ultra-moon"]}],"genderRatio":4,"hatchSteps":5100,"pokedexNumbers":[{"dex":"national","number":708},{"dex":"kalos-mountain","number":61},{"dex":"original-alola","number":196},{"dex":"original-akala","number":123},{"dex":"updated-alola","number":250},{"dex":"updated-akala","number":151},{"dex":"galar","number":338},{"dex":"crown-tundra","number":33},{"dex":"kitakami","number":68},{"dex":"lumiose-city","number":182}]}