{"id":795,"name":"pheromosa","image":"https://raw.githubusercontent.com/PokeAPI/sprites/master/sprites/pokemon/other/home/795.png","types":["bug","fighting"],"abilities":["beast-boost"],"height":18,"weight":250,"stats":[{"base_stat":71,"effort":0,"stat":{"name":"hp","url":"https://pokeapi.co/api/v2/stat/1/"}},{"base_stat":137,"effort":0,"stat":{"name":"attack","url":"https://pokeapi.co/api/v2/stat/2/"}},{"base_stat":37,"effort":0,"stat":{"name":"defense","url":"https://pokeapi.co/api/v2/stat/3/"}},{"base_stat":137,"effort":0,"stat":{"name":"special-attack","url":"https://pokeapi.co/api/v2/stat/4/"}},{"base_stat":37,"effort":0,"stat":{"name":"special-defense","url":"https://pokeapi.co/api/v2/stat/5/"}},{"base_stat":151,"effort":3,"stat":{"name":"speed","url":"https://pokeapi.co/api/v2/stat/6/"}}],"base_experience":257,"total_stats":570,"stat_category":"speedster","generation":"generation-vii","is_legendary":false,"is_mythical":false,"habitat":null,"color":"white","shape":"humanoid","capture_rate":45,"growth_rate":"slow","egg_groups":["no-eggs"],"flavor_text":"One of the dangerous Ultra Beasts, it has been spotted running across the land at terrific speeds.","rarity_tier":"rare","size_category":"medium","evolutionChain":{"species":"pheromosa","speciesId":795,"trigger":null,"triggerDetail":null,"evolvesTo":[]},"moves":[{"name":"rapid-spin","type":"normal","power":50,"accuracy":100,"pp":40,"damageClass":"physical","effect":"Frees the user from binding moves, removes Leech Seed, and blows away Spikes.","learnMethod":"level-up","levelLearned":1},{"name":"feint","type":"normal","power":30,"accuracy":100,"pp":10,"damageClass":"physical","effect":"Hits through Protect and Detect.","learnMethod":"level-up","levelLearned":1},{"name":"leer","type":"normal","power":null,"accuracy":100,"pp":30,"damageClass":"status","effect":"Lowers the target’s Defense by one stage.","learnMethod":"level-up","levelLearned":5},{"name":"quick-guard","type":"fighting","power":null,"accuracy":null,"pp":15,"damageClass":"status","effect":"Prevents any priority moves from hitting friendly Pokémon this turn.","learnMethod":"level-up","levelLearned":10},{"name":"bug-bite","type":"bug","power":60,"accuracy":100,"pp":20,"damageClass":"physical","effect":"If target has a berry, inflicts double damage and uses the berry.","learnMethod":"level-up","levelLearned":15},{"name":"silver-wind","type":"bug","power":60,"accuracy":100,"pp":5,"damageClass":"special","effect":"Has a 10% chance to raise all of the user’s stats by one stage.","learnMethod":"level-up","levelLearned":23},{"name":"double-kick","type":"fighting","power":30,"accuracy":100,"pp":30,"damageClass":"physical","effect":"Hits twice in one turn.","learnMethod":"level-up","levelLearned":25},{"name":"triple-kick","type":"fighting","power":10,"accuracy":90,"pp":10,"damageClass":"physical","effect":"Hits three times, increasing power by 100% with each successful hit.","learnMethod":"level-up","levelLearned":30},{"name":"jump-kick","type":"fighting","power":100,"accuracy":95,"pp":10,"damageClass":"physical","effect":"If the user misses, it takes half the damage it would have inflicted in recoil.","learnMethod":"level-up","levelLearned":31},{"name":"stomp","type":"normal","power":65,"accuracy":100,"pp":20,"damageClass":"physical","effect":"Has a 30% chance to make the target flinch.","learnMethod":"level-up","levelLearned":35},{"name":"lunge","type":"bug","power":80,"accuracy":100,"pp":15,"damageClass":"physical","effect":"Lowers the target’s Attack by one stage after inflicting damage.","learnMethod":"level-up","levelLearned":45},{"name":"me-first","type":"normal","power":null,"accuracy":null,"pp":20,"damageClass":"status","effect":"Uses the target’s move against it before it attacks, with power increased by half.","learnMethod":"level-up","levelLearned":59},{"name":"quiver-dance","type":"bug","power":null,"accuracy":null,"pp":20,"damageClass":"status","effect":"Raises the user’s Special Attack, Special Defense, and Speed by one stage each.","learnMethod":"level-up","levelLearned":65},{"name":"high-jump-kick","type":"fighting","power":130,"accuracy":90,"pp":10,"damageClass":"physical","effect":"If the user misses, it takes half the damage it would have inflicted in recoil.","learnMethod":"level-up","levelLearned":70},{"name":"agility","type":"psychic","power":null,"accuracy":null,"pp":30,"damageClass":"status","effect":"Raises the user’s Speed by two stages.","learnMethod":"machine","levelLearned":null},{"name":"assurance","type":"dark","power":60,"accuracy":100,"pp":10,"damageClass":"physical","effect":"Power is doubled if the target has already received damage this turn.","learnMethod":"machine","levelLearned":null},{"name":"blizzard","type":"ice","power":110,"accuracy":70,"pp":5,"damageClass":"special","effect":"Has a 10% chance to freeze the target.","learnMethod":"machine","levelLearned":null},{"name":"bounce","type":"flying","power":85,"accuracy":85,"pp":5,"damageClass":"physical","effect":"User bounces high into the air, dodging all attacks, and hits next turn.","learnMethod":"machine","levelLearned":null},{"name":"brick-break","type":"fighting","power":75,"accuracy":100,"pp":15,"damageClass":"physical","effect":"Destroys Reflect and Light Screen.","learnMethod":"machine","levelLearned":null},{"name":"bug-buzz","type":"bug","power":90,"accuracy":100,"pp":10,"damageClass":"special","effect":"Has a 10% chance to lower the target’s Special Defense by one stage.","learnMethod":"machine","levelLearned":null},{"name":"close-combat","type":"fighting","power":120,"accuracy":100,"pp":5,"damageClass":"physical","effect":"Lowers the user’s Defense and Special Defense by one stage after inflicting damage.","learnMethod":"machine","levelLearned":null},{"name":"confide","type":"normal","power":null,"accuracy":null,"pp":20,"damageClass":"status","effect":"Lowers the target’s Special Attack by one stage.","learnMethod":"machine","levelLearned":null},{"name":"double-team","type":"normal","power":null,"accuracy":null,"pp":15,"damageClass":"status","effect":"Raises the user’s evasion by one stage.","learnMethod":"machine","levelLearned":null},{"name":"drill-run","type":"ground","power":80,"accuracy":95,"pp":10,"damageClass":"physical","effect":"Has an increased chance for a critical hit.","learnMethod":"machine","levelLearned":null},{"name":"echoed-voice","type":"normal","power":40,"accuracy":100,"pp":15,"damageClass":"special","effect":"Power increases by 100% for each consecutive use by any friendly Pokémon, to a maximum of 200.","learnMethod":"machine","levelLearned":null},{"name":"electroweb","type":"electric","power":55,"accuracy":95,"pp":15,"damageClass":"special","effect":"Lowers the target’s Speed by one stage.","learnMethod":"machine","levelLearned":null},{"name":"endure","type":"normal","power":null,"accuracy":null,"pp":10,"damageClass":"status","effect":"Prevents the user’s HP from lowering below 1 this turn.","learnMethod":"machine","levelLearned":null},{"name":"facade","type":"normal","power":70,"accuracy":100,"pp":20,"damageClass":"physical","effect":"Power doubles if user is burned, paralyzed, or poisoned.","learnMethod":"machine","levelLearned":null},{"name":"false-swipe","type":"normal","power":40,"accuracy":100,"pp":40,"damageClass":"physical","effect":"Cannot lower the target’s HP below 1.","learnMethod":"machine","levelLearned":null},{"name":"fling","type":"dark","power":null,"accuracy":100,"pp":10,"damageClass":"physical","effect":"Throws held item at the target; power depends on the item.","learnMethod":"machine","levelLearned":null},{"name":"focus-blast","type":"fighting","power":120,"accuracy":70,"pp":5,"damageClass":"special","effect":"Has a 10% chance to lower the target’s Special Defense by one stage.","learnMethod":"machine","levelLearned":null},{"name":"foul-play","type":"dark","power":95,"accuracy":100,"pp":15,"damageClass":"physical","effect":"Calculates damage with the target’s attacking stat.","learnMethod":"machine","levelLearned":null},{"name":"frustration","type":"normal","power":null,"accuracy":100,"pp":20,"damageClass":"physical","effect":"Power increases as happiness decreases, up to a maximum of 102.","learnMethod":"machine","levelLearned":null},{"name":"giga-impact","type":"normal","power":150,"accuracy":90,"pp":5,"damageClass":"physical","effect":"User foregoes its next turn to recharge.","learnMethod":"machine","levelLearned":null},{"name":"hidden-power","type":"normal","power":60,"accuracy":100,"pp":15,"damageClass":"special","effect":"Power and type depend upon user’s IVs.  Power can range from 30 to 70.","learnMethod":"machine","levelLearned":null},{"name":"hyper-beam","type":"normal","power":150,"accuracy":90,"pp":5,"damageClass":"special","effect":"User foregoes its next turn to recharge.","learnMethod":"machine","levelLearned":null},{"name":"ice-beam","type":"ice","power":90,"accuracy":100,"pp":10,"damageClass":"special","effect":"Has a 10% chance to freeze the target.","learnMethod":"machine","levelLearned":null},{"name":"icy-wind","type":"ice","power":55,"accuracy":95,"pp":15,"damageClass":"special","effect":"Has a 100% chance to lower the target’s Speed by one stage.","learnMethod":"machine","levelLearned":null},{"name":"low-kick","type":"fighting","power":null,"accuracy":100,"pp":20,"damageClass":"physical","effect":"Inflicts more damage to heavier targets, with a maximum of 120 power.","learnMethod":"machine","levelLearned":null},{"name":"low-sweep","type":"fighting","power":65,"accuracy":100,"pp":20,"damageClass":"physical","effect":"Lowers the target’s Speed by one stage.","learnMethod":"machine","levelLearned":null},{"name":"outrage","type":"dragon","power":120,"accuracy":100,"pp":10,"damageClass":"physical","effect":"Hits every turn for 2-3 turns, then confuses the user.","learnMethod":"machine","levelLearned":null},{"name":"poison-jab","type":"poison","power":80,"accuracy":100,"pp":20,"damageClass":"physical","effect":"Has a 30% chance to poison the target.","learnMethod":"machine","levelLearned":null},{"name":"protect","type":"normal","power":null,"accuracy":null,"pp":10,"damageClass":"status","effect":"Prevents any moves from hitting the user this turn.","learnMethod":"machine","levelLearned":null},{"name":"rest","type":"psychic","power":null,"accuracy":null,"pp":5,"damageClass":"status","effect":"User sleeps for two turns, completely healing itself.","learnMethod":"machine","levelLearned":null},{"name":"return","type":"normal","power":null,"accuracy":100,"pp":20,"damageClass":"physical","effect":"Power increases with happiness, up to a maximum of 102.","learnMethod":"machine","levelLearned":null},{"name":"roost","type":"flying","power":null,"accuracy":null,"pp":5,"damageClass":"status","effect":"Heals the user by half its max HP.","learnMethod":"machine","levelLearned":null},{"name":"round","type":"normal","power":60,"accuracy":100,"pp":15,"damageClass":"special","effect":"Has double power if it’s used more than once per turn.","learnMethod":"machine","levelLearned":null},{"name":"sleep-talk","type":"normal","power":null,"accuracy":null,"pp":10,"damageClass":"status","effect":"Randomly uses one of the user’s other three moves.  Only works if the user is sleeping.","learnMethod":"machine","levelLearned":null},{"name":"snore","type":"normal","power":50,"accuracy":100,"pp":15,"damageClass":"special","effect":"Has a 30% chance to make the target flinch.  Only works if the user is sleeping.","learnMethod":"machine","levelLearned":null},{"name":"speed-swap","type":"psychic","power":null,"accuracy":null,"pp":10,"damageClass":"status","effect":"Exchanges the user’s Speed with the target’s.","learnMethod":"machine","levelLearned":null},{"name":"substitute","type":"normal","power":null,"accuracy":null,"pp":10,"damageClass":"status","effect":"Transfers 1/4 of the user’s max HP into a doll, protecting the user from further damage or status changes until it breaks.","learnMethod":"machine","levelLearned":null},{"name":"swagger","type":"normal","power":null,"accuracy":85,"pp":15,"damageClass":"status","effect":"Raises the target’s Attack by two stages and confuses the target.","learnMethod":"machine","levelLearned":null},{"name":"swift","type":"normal","power":60,"accuracy":null,"pp":20,"damageClass":"special","effect":"Never misses.","learnMethod":"machine","levelLearned":null},{"name":"taunt","type":"dark","power":null,"accuracy":100,"pp":20,"damageClass":"status","effect":"For the next few turns, the target can only use damaging moves.","learnMethod":"machine","levelLearned":null},{"name":"throat-chop","type":"dark","power":80,"accuracy":100,"pp":15,"damageClass":"physical","effect":"Prevents the target from using sound-based moves for two turns.","learnMethod":"machine","levelLearned":null},{"name":"torment","type":"dark","power":null,"accuracy":100,"pp":15,"damageClass":"status","effect":"Prevents the target from using the same move twice in a row.","learnMethod":"machine","levelLearned":null},{"name":"toxic","type":"poison","power":null,"accuracy":90,"pp":10,"damageClass":"status","effect":"Badly poisons the target, inflicting more damage every turn.","learnMethod":"machine","levelLearned":null},{"name":"u-turn","type":"bug","power":70,"accuracy":100,"pp":20,"damageClass":"physical","effect":"User must switch out after attacking.","learnMethod":"machine","levelLearned":null},{"name":"block","type":"normal","power":null,"accuracy":null,"pp":5,"damageClass":"status","effect":"Prevents the target from leaving battle.","learnMethod":"tutor","levelLearned":null},{"name":"coaching","type":"fighting","power":null,"accuracy":null,"pp":10,"damageClass":"status","effect":"Inflicts regular damage with no additional effect.","learnMethod":"tutor","levelLearned":null},{"name":"laser-focus","type":"normal","power":null,"accuracy":null,"pp":30,"damageClass":"status","effect":"Guarantees a critical hit with the user’s next move.","learnMethod":"tutor","levelLearned":null},{"name":"shock-wave","type":"electric","power":60,"accuracy":null,"pp":20,"damageClass":"special","effect":"Never misses.","learnMethod":"tutor","levelLearned":null},{"name":"signal-beam","type":"bug","power":75,"accuracy":100,"pp":15,"damageClass":"special","effect":"Has a 10% chance to confuse the target.","learnMethod":"tutor","levelLearned":null},{"name":"skitter-smack","type":"bug","power":70,"accuracy":90,"pp":10,"damageClass":"physical","effect":"Inflicts regular damage with no additional effect.","learnMethod":"tutor","levelLearned":null},{"name":"snatch","type":"dark","power":null,"accuracy":null,"pp":10,"damageClass":"status","effect":"Steals the target’s move, if it’s self-targeted.","learnMethod":"tutor","levelLearned":null},{"name":"triple-axel","type":"ice","power":20,"accuracy":90,"pp":10,"damageClass":"physical","effect":"Inflicts regular damage with no additional effect.","learnMethod":"tutor","levelLearned":null}],"abilitiesDetailed":[{"name":"beast-boost","isHidden":false,"effect":"Raises this Pokémon's highest stat by one stage when it faints another Pokémon."}],"sprites":{"official":"https://raw.githubusercontent.com/PokeAPI/sprites/master/sprites/pokemon/other/official-artwork/795.png","shiny":"https://raw.githubusercontent.com/PokeAPI/sprites/master/sprites/pokemon/other/official-artwork/shiny/795.png","home":"https://raw.githubusercontent.com/PokeAPI/sprites/master/sprites/pokemon/other/home/795.png","animated":null},"forms":[],"encounters":[{"location":"Ultra Space Ultra Desert","games":["ultra-moon"]},{"location":"Verdant Cavern Trial Site","games":["moon"]},{"location":"Verdant Cavern  Trial Site Area","games":["moon"]}],"genderRatio":-1,"hatchSteps":30600,"pokedexNumbers":[{"dex":"national","number":795},{"dex":"original-alola","number":295},{"dex":"updated-alola","number":395}]}